{
  "schema_version": "1",
  "updated_at": "2026-03-10T00:00:00Z",
  "plugins": {
    "python-fastapi": {
      "id": "python-fastapi",
      "name": "Python FastAPI",
      "version": "1.0.0",
      "kind": "language",
      "platform": "backend",
      "language": "python",
      "description": "Python FastAPI backend — REST API, async, Pydantic models",
      "author": "nexus",
      "min_nexus": "1.0.0",
      "capabilities": ["http_server", "orm", "authentication", "rest_api"],
      "download_url": "https://raw.githubusercontent.com/hackersfun369/nexus/main/plugins/packages/python-fastapi-1.0.0.json",
      "sha256": ""
    },
    "kotlin-android": {
      "id": "kotlin-android",
      "name": "Kotlin Android",
      "version": "1.2.0",
      "kind": "language",
      "platform": "android",
      "language": "kotlin",
      "description": "Kotlin for Android — MVVM, Jetpack Compose, Room, Retrofit",
      "author": "nexus",
      "min_nexus": "1.0.0",
      "capabilities": ["ui_components", "navigation", "local_database", "networking"],
      "download_url": "https://raw.githubusercontent.com/hackersfun369/nexus/main/plugins/packages/kotlin-android-1.2.0.json",
      "sha256": ""
    },
    "react-web": {
      "id": "react-web",
      "name": "React Web",
      "version": "3.1.0",
      "kind": "framework",
      "platform": "web",
      "language": "typescript",
      "description": "React + TypeScript web app — Vite, Tailwind, React Router, Zustand",
      "author": "nexus",
      "min_nexus": "1.0.0",
      "capabilities": ["ui_components", "routing", "state_management", "styling"],
      "download_url": "https://raw.githubusercontent.com/hackersfun369/nexus/main/plugins/packages/react-web-3.1.0.json",
      "sha256": ""
    },
    "flutter-mobile": {
      "id": "flutter-mobile",
      "name": "Flutter Mobile",
      "version": "1.0.0",
      "kind": "language",
      "platform": "all",
      "language": "dart",
      "description": "Flutter — cross-platform mobile, web and desktop from one codebase",
      "author": "nexus",
      "min_nexus": "1.0.0",
      "capabilities": ["ui_components", "navigation", "local_database", "networking", "cross_platform"],
      "download_url": "https://raw.githubusercontent.com/hackersfun369/nexus/main/plugins/packages/flutter-mobile-1.0.0.json",
      "sha256": ""
    },
    "go-backend": {
      "id": "go-backend",
      "name": "Go Backend",
      "version": "1.0.0",
      "kind": "language",
      "platform": "backend",
      "language": "go",
      "description": "Go backend — chi router, SQLite/Postgres, clean architecture",
      "author": "nexus",
      "min_nexus": "1.0.0",
      "capabilities": ["http_server", "orm", "authentication", "rest_api", "cli"],
      "download_url": "https://raw.githubusercontent.com/hackersfun369/nexus/main/plugins/packages/go-backend-1.0.0.json",
      "sha256": ""
    },
    "swift-ios": {
      "id": "swift-ios",
      "name": "Swift iOS",
      "version": "1.0.0",
      "kind": "language",
      "platform": "mac",
      "language": "swift",
      "description": "Swift for iOS/macOS — SwiftUI, Combine, CoreData",
      "author": "nexus",
      "min_nexus": "1.0.0",
      "capabilities": ["ui_components", "navigation", "local_database", "networking"],
      "download_url": "https://raw.githubusercontent.com/hackersfun369/nexus/main/plugins/packages/swift-ios-1.0.0.json",
      "sha256": ""
    },
    "electron-desktop": {
      "id": "electron-desktop",
      "name": "Electron Desktop",
      "version": "1.0.0",
      "kind": "platform",
      "platform": "windows",
      "language": "typescript",
      "description": "Electron — cross-platform desktop apps with web technologies",
      "author": "nexus",
      "min_nexus": "1.0.0",
      "capabilities": ["ui_components", "file_system", "system_tray", "auto_update"],
      "download_url": "https://raw.githubusercontent.com/hackersfun369/nexus/main/plugins/packages/electron-desktop-1.0.0.json",
      "sha256": ""
    },
    "rust-cli": {
      "id": "rust-cli",
      "name": "Rust CLI",
      "version": "1.0.0",
      "kind": "language",
      "platform": "cli",
      "language": "rust",
      "description": "Rust CLI tool — clap, tokio, serde, cross-platform binary",
      "author": "nexus",
      "min_nexus": "1.0.0",
      "capabilities": ["cli", "async", "serialization", "cross_platform"],
      "download_url": "https://raw.githubusercontent.com/hackersfun369/nexus/main/plugins/packages/rust-cli-1.0.0.json",
      "sha256": ""
    }
  }
}
